uuid_upload_path/__init__.py
uuid_upload_path/storage.py
uuid_upload_path/tests.py
uuid_upload_path/uuid.py
django_file_upload_to-2.0.0.dist-info/LICENSE
django_file_upload_to-2.0.0.dist-info/METADATA
django_file_upload_to-2.0.0.dist-info/WHEEL
django_file_upload_to-2.0.0.dist-info/top_level.txt
django_file_upload_to-2.0.0.dist-info/zip-safe
django_file_upload_to-2.0.0.dist-info/RECORD
