Metadata-Version: 2.1
Name: django-file-upload-to
Version: 2.0.0
Summary: Generate short UUIDs and use them as paths for uploaded media files in Django.
Home-page: https://github.com/panttojo/django-file-upload-to
Author: Daniel Pantoja
Author-email: panttojo@yandex.com
License: BSD
Platform: UNKNOWN
Classifier: Development Status :: 5 - Production/Stable
Classifier: Environment :: Web Environment
Classifier: Framework :: Django
Classifier: Intended Audience :: Developers
Classifier: License :: OSI Approved :: BSD License
Classifier: Operating System :: OS Independent
Classifier: Programming Language :: Python
Classifier: Programming Language :: Python :: 3
Classifier: Programming Language :: Python :: 3.4
Classifier: Programming Language :: Python :: 3.7
Classifier: Topic :: Internet :: WWW/HTTP
Requires-Python: >=3.4
